pycurl.cpython-314t-darwin.so
pycurl-7.45.7.data/data/share/doc/pycurl/INSTALL.rst
pycurl-7.45.7.data/data/share/doc/pycurl/COPYING-LGPL
pycurl-7.45.7.data/data/share/doc/pycurl/COPYING-MIT
pycurl-7.45.7.data/data/share/doc/pycurl/RELEASE-NOTES.rst
pycurl-7.45.7.data/data/share/doc/pycurl/ChangeLog
pycurl-7.45.7.data/data/share/doc/pycurl/AUTHORS
pycurl-7.45.7.data/data/share/doc/pycurl/README.rst
pycurl-7.45.7.data/data/share/doc/pycurl/examples/xmlrpc_curl.py
pycurl-7.45.7.data/data/share/doc/pycurl/examples/multi-socket_action-select.py
pycurl-7.45.7.data/data/share/doc/pycurl/examples/opensocketexception.py
pycurl-7.45.7.data/data/share/doc/pycurl/examples/retriever.py
pycurl-7.45.7.data/data/share/doc/pycurl/examples/ssh_keyfunction.py
pycurl-7.45.7.data/data/share/doc/pycurl/examples/sfquery.py
pycurl-7.45.7.data/data/share/doc/pycurl/examples/retriever-multi.py
pycurl-7.45.7.data/data/share/doc/pycurl/examples/smtp.py
pycurl-7.45.7.data/data/share/doc/pycurl/examples/linksys.py
pycurl-7.45.7.data/data/share/doc/pycurl/examples/file_upload.py
pycurl-7.45.7.data/data/share/doc/pycurl/examples/basicfirst.py
pycurl-7.45.7.data/data/share/doc/pycurl/examples/quickstart/put_buffer.py
pycurl-7.45.7.data/data/share/doc/pycurl/examples/quickstart/form_post.py
pycurl-7.45.7.data/data/share/doc/pycurl/examples/quickstart/put_file.py
pycurl-7.45.7.data/data/share/doc/pycurl/examples/quickstart/file_upload_buffer.py
pycurl-7.45.7.data/data/share/doc/pycurl/examples/quickstart/follow_redirect.py
pycurl-7.45.7.data/data/share/doc/pycurl/examples/quickstart/file_upload_real.py
pycurl-7.45.7.data/data/share/doc/pycurl/examples/quickstart/get_python2.py
pycurl-7.45.7.data/data/share/doc/pycurl/examples/quickstart/file_upload_real_fancy.py
pycurl-7.45.7.data/data/share/doc/pycurl/examples/quickstart/get_python2_https.py
pycurl-7.45.7.data/data/share/doc/pycurl/examples/quickstart/get_python3_https.py
pycurl-7.45.7.dist-info/RECORD
pycurl-7.45.7.dist-info/WHEEL
pycurl-7.45.7.dist-info/top_level.txt
pycurl-7.45.7.dist-info/METADATA
pycurl-7.45.7.dist-info/licenses/COPYING-LGPL
pycurl-7.45.7.dist-info/licenses/COPYING-MIT
pycurl-7.45.7.dist-info/licenses/AUTHORS
