Metadata-Version: 2.4
Name: pycurl
Version: 7.45.7
Summary: PycURL -- A Python Interface To The cURL library
Home-page: http://pycurl.io/
Author: Kjetil Jacobsen, Markus F.X.J. Oberhumer, Oleg Pudeyev
Author-email: kjetilja@gmail.com, markus@oberhumer.com, oleg@bsdpower.com
Maintainer: Oleg Pudeyev
Maintainer-email: oleg@bsdpower.com
License: LGPL/MIT
Keywords: curl,libcurl,urllib,wget,download,file transfer,http,www
Platform: All
Classifier: Development Status :: 5 - Production/Stable
Classifier: Environment :: Web Environment
Classifier: Intended Audience :: Developers
Classifier: License :: OSI Approved :: GNU Library or Lesser General Public License (LGPL)
Classifier: License :: OSI Approved :: MIT License
Classifier: Operating System :: Microsoft :: Windows
Classifier: Operating System :: POSIX
Classifier: Programming Language :: Python :: 3
Classifier: Programming Language :: Python :: 3.9
Classifier: Programming Language :: Python :: 3.10
Classifier: Programming Language :: Python :: 3.11
Classifier: Programming Language :: Python :: 3.12
Classifier: Programming Language :: Python :: 3.13
Classifier: Programming Language :: Python :: 3.14
Classifier: Topic :: Internet :: File Transfer Protocol (FTP)
Classifier: Topic :: Internet :: WWW/HTTP
Requires-Python: >=3.5
License-File: COPYING-LGPL
License-File: COPYING-MIT
License-File: AUTHORS
Dynamic: author
Dynamic: author-email
Dynamic: classifier
Dynamic: description
Dynamic: home-page
Dynamic: keywords
Dynamic: license
Dynamic: license-file
Dynamic: maintainer
Dynamic: maintainer-email
Dynamic: platform
Dynamic: requires-python
Dynamic: summary
